LICENSE.txt
MANIFEST.in
README.rst
Tool.py
setup.py
reidpy.egg-info/PKG-INFO
reidpy.egg-info/SOURCES.txt
reidpy.egg-info/dependency_links.txt
reidpy.egg-info/top_level.txt
reidtest/__init__.py
reidtest/reidrun.py