Metadata-Version: 1.0
Name: reidpy
Version: 1.0.0
Summary: **xxx**
